derpy/__init__.py
derpy/build/__init__.py
derpy/build/base_image.py
derpy/build/diff.py
derpy/build/engine.py
derpy/build/exceptions.py
derpy/build/isolation.py
derpy/build/layers.py
derpy/build/models.py
derpy/build/pipeline.py
derpy/cli/__init__.py
derpy/cli/banner.py
derpy/cli/main.py
derpy/core/__init__.py
derpy/core/auth.py
derpy/core/config.py
derpy/core/exceptions.py
derpy/core/logging.py
derpy/core/platform.py
derpy/dockerfile/__init__.py
derpy/dockerfile/handlers.py
derpy/dockerfile/parser.py
derpy/oci/__init__.py
derpy/oci/layout.py
derpy/oci/models.py
derpy/registry/__init__.py
derpy/registry/client.py
derpy/storage/__init__.py
derpy/storage/manager.py
derpy_tool-0.1.1.dist-info/licenses/LICENSE
derpy_tool-0.1.1.dist-info/METADATA
derpy_tool-0.1.1.dist-info/WHEEL
derpy_tool-0.1.1.dist-info/entry_points.txt
derpy_tool-0.1.1.dist-info/top_level.txt
derpy_tool-0.1.1.dist-info/RECORD
