Metadata-Version: 2.4
Name: derpy-tool
Version: 0.1.1
Summary: A simple container tool, made with AI, for building, managing, and distributing OCI-compliant container images
Author-email: Adonis Cesar Legón Campo <alegon@gmail.com>
Maintainer-email: Adonis Cesar Legón Campo <alegon@gmail.com>
License: MIT
Project-URL: Homepage, https://github.com/adonis-legon/derpy
Project-URL: Repository, https://github.com/adonis-legon/derpy.git
Project-URL: Issues, https://github.com/adonis-legon/derpy/issues
Project-URL: Documentation, https://derpy.readthedocs.io
Keywords: container,docker,oci,cli,build,images
Classifier: Development Status :: 3 - Alpha
Classifier: Environment :: Console
Classifier: Intended Audience :: Developers
Classifier: License :: OSI Approved :: MIT License
Classifier: Operating System :: OS Independent
Classifier: Operating System :: Microsoft :: Windows
Classifier: Operating System :: POSIX :: Linux
Classifier: Operating System :: MacOS
Classifier: Programming Language :: Python :: 3
Classifier: Programming Language :: Python :: 3.10
Classifier: Programming Language :: Python :: 3.11
Classifier: Programming Language :: Python :: 3.12
Classifier: Programming Language :: Python :: 3.13
Classifier: Topic :: Software Development :: Build Tools
Classifier: Topic :: System :: Systems Administration
Requires-Python: >=3.10
License-File: LICENSE
Requires-Dist: PyYAML>=6.0
Requires-Dist: click>=8.0.0
Requires-Dist: requests>=2.28.0
Provides-Extra: dev
Requires-Dist: pytest>=7.0.0; extra == "dev"
Requires-Dist: pytest-cov>=4.0.0; extra == "dev"
Requires-Dist: black>=23.0.0; extra == "dev"
Requires-Dist: flake8>=6.0.0; extra == "dev"
Requires-Dist: mypy>=1.0.0; extra == "dev"
Dynamic: license-file
